pcapgen/__init__.py
pcapgen/pft.py
pcapgen/pgt.py
pcapgen/pgtlib.py
pcapgen-0.8.dist-info/METADATA
pcapgen-0.8.dist-info/WHEEL
pcapgen-0.8.dist-info/dependency_links.txt
pcapgen-0.8.dist-info/top_level.txt
pcapgen-0.8.dist-info/RECORD
