Metadata-Version: 2.1
Name: pcapgen
Version: 0.8
Summary: Module to generate PCAPs from any input file. This is a modified version of PGT tool which wasdeveloped earlier by, Andrewg Felinemenace.
Home-page: https://pypi.org/project/python-pcapgen/
Author: Sujit Ghosal
Author-email: synack@outlook.com
License: BSD
Keywords: pcapgen pcap wireshark pgt http imap smtp ftp protocol
Platform: UNKNOWN
Classifier: Environment :: Console
Classifier: Operating System :: MacOS :: MacOS X
Classifier: Operating System :: Microsoft :: Windows
Classifier: Operating System :: POSIX :: Linux
Classifier: Programming Language :: Python :: 3.7
Classifier: Topic :: Utilities
Classifier: Topic :: Internet
Classifier: Topic :: System :: Networking
Classifier: Intended Audience :: Developers
Requires-Dist: python-magic (>=0.4.18)
Requires-Dist: kamene
